xtermgui/__init__.py
xtermgui/control/__init__.py
xtermgui/control/colour.py
xtermgui/control/colours.py
xtermgui/control/cursor.py
xtermgui/control/rgb.py
xtermgui/control/rgbs.py
xtermgui/control/style.py
xtermgui/control/styles.py
xtermgui/control/text.py
xtermgui/control/types.py
xtermgui/geometry/__init__.py
xtermgui/geometry/coordinate.py
xtermgui/geometry/region.py
xtermgui/gui/__init__.py
xtermgui/gui/gui.py
xtermgui/gui/keyboard_interaction.py
xtermgui/gui/mouse_interaction.py
xtermgui/input/__init__.py
xtermgui/input/event.py
xtermgui/input/events.py
xtermgui/input/input.py
xtermgui/input/keyboard_codes.py
xtermgui/input/keyboard_event.py
xtermgui/input/mouse_codes.py
xtermgui/input/mouse_event.py
xtermgui/input/setup.py
xtermgui/layered_gui/__init__.py
xtermgui/layered_gui/gui.py
xtermgui/layered_gui/layer.py
XtermGUI-0.1.2.dist-info/LICENSE
XtermGUI-0.1.2.dist-info/METADATA
XtermGUI-0.1.2.dist-info/WHEEL
XtermGUI-0.1.2.dist-info/top_level.txt
XtermGUI-0.1.2.dist-info/RECORD
