Metadata-Version: 2.1
Name: XtermGUI
Version: 0.1.2
Summary: A lightweight, expressive GUI framework for compatible terminals
Author-email: Kieran Lock <kieran.lock@outlook.com>
License: GNU GENERAL PUBLIC LICENSE
Project-URL: GitHub, https://github.com/Kieran-Lock/XtermGUI
Project-URL: Documentation, https://github.com/Kieran-Lock/XtermGUI/blob/main/DOCUMENTATION.md
Project-URL: License, https://github.com/Kieran-Lock/XtermGUI/blob/main/LICENSE
Keywords: gui,framework,xterm,zero-dependency,terminal-based
Classifier: Development Status :: 3 - Alpha
Classifier: Environment :: Console
Classifier: License :: OSI Approved :: GNU General Public License v3 (GPLv3)
Classifier: Operating System :: POSIX :: Linux
Classifier: Programming Language :: Python :: 3.8
Classifier: Intended Audience :: Developers
Requires-Python: >=3.8
License-File: LICENSE
